poetry_binary_plugin/__init__.py
poetry_binary_plugin/plugin.py
poetry_binary_plugin-1.0.0a3.dist-info/METADATA
poetry_binary_plugin-1.0.0a3.dist-info/WHEEL
poetry_binary_plugin-1.0.0a3.dist-info/entry_points.txt
poetry_binary_plugin-1.0.0a3.dist-info/RECORD
